blockout/__init__.py
blockout/cli.py
blockout/commands/__init__.py
blockout-0.0.1.dev1.data/data/share/blockout/config.py.dist
blockout-0.0.1.dev1.dist-info/AUTHORS
blockout-0.0.1.dev1.dist-info/LICENSE
blockout-0.0.1.dev1.dist-info/METADATA
blockout-0.0.1.dev1.dist-info/WHEEL
blockout-0.0.1.dev1.dist-info/entry_points.txt
blockout-0.0.1.dev1.dist-info/pbr.json
blockout-0.0.1.dev1.dist-info/top_level.txt
blockout-0.0.1.dev1.dist-info/RECORD
